{
  "main": {
    "id": "c1ecdea889f9689f",
    "type": "split",
    "children": [
      {
        "id": "306a8826a9ee460e",
        "type": "tabs",
        "children": [
          {
            "id": "ae905018e9ddedf3",
            "type": "leaf",
            "state": {
              "type": "markdown",
              "state": {
                "file": "utf/引力光速统一方程/Gravitational Light Speed Unification Equation Theoretical Derivation and Verification from Spatial Dynamics Principles to Constant Unification.md",
                "mode": "source",
                "source": false
              },
              "icon": "lucide-file",
              "title": "Gravitational Light Speed Unification Equation Theoretical Derivation and Verification from Spatial Dynamics Principles to Constant Unification"
            }
          }
        ]
      }
    ],
    "direction": "vertical"
  },
  "left": {
    "id": "a70e76cb36f96746",
    "type": "split",
    "children": [
      {
        "id": "6252fb3190da18bc",
        "type": "tabs",
        "children": [
          {
            "id": "9fb81b15c609cf91",
            "type": "leaf",
            "state": {
              "type": "file-explorer",
              "state": {
                "sortOrder": "alphabetical",
                "autoReveal": false
              },
              "icon": "lucide-folder-closed",
              "title": "文件列表"
            }
          },
          {
            "id": "c07c3f52c84c7475",
            "type": "leaf",
            "state": {
              "type": "search",
              "state": {
                "query": "tag:#NewChat",
                "matchingCase": false,
                "explainSearch": false,
                "collapseAll": false,
                "extraContext": false,
                "sortOrder": "alphabetical"
              },
              "icon": "lucide-search",
              "title": "搜索"
            }
          },
          {
            "id": "68d3133b2f1a5032",
            "type": "leaf",
            "state": {
              "type": "bookmarks",
              "state": {},
              "icon": "lucide-bookmark",
              "title": "书签"
            }
          }
        ]
      }
    ],
    "direction": "horizontal",
    "width": 399.5
  },
  "right": {
    "id": "16158ab9e45ddd91",
    "type": "split",
    "children": [
      {
        "id": "c29ce5ed8cd49025",
        "type": "tabs",
        "children": [
          {
            "id": "ac5a3d018dc6223c",
            "type": "leaf",
            "state": {
              "type": "backlink",
              "state": {
                "file": "utf/引力光速统一方程/基于张祥前统一场论的引力常数G与光速c关系推导及理论验证引力光速统一方程.md",
                "collapseAll": false,
                "extraContext": false,
                "sortOrder": "alphabetical",
                "showSearch": false,
                "searchQuery": "",
                "backlinkCollapsed": false,
                "unlinkedCollapsed": true
              },
              "icon": "links-coming-in",
              "title": "基于张祥前统一场论的引力常数G与光速c关系推导及理论验证引力光速统一方程 的反向链接列表"
            }
          },
          {
            "id": "3dd42f63da084ddf",
            "type": "leaf",
            "state": {
              "type": "outgoing-link",
              "state": {
                "file": "未命名.base",
                "linksCollapsed": false,
                "unlinkedCollapsed": true
              },
              "icon": "links-going-out",
              "title": "未命名 的出链列表"
            }
          },
          {
            "id": "46140b785ac04f87",
            "type": "leaf",
            "state": {
              "type": "tag",
              "state": {
                "sortOrder": "frequency",
                "useHierarchy": true,
                "showSearch": false,
                "searchQuery": ""
              },
              "icon": "lucide-tags",
              "title": "标签"
            }
          },
          {
            "id": "59dca15b9d787f7e",
            "type": "leaf",
            "state": {
              "type": "outline",
              "state": {
                "file": "utf/引力光速统一方程/基于张祥前统一场论的引力常数G与光速c关系推导及理论验证引力光速统一方程.md",
                "followCursor": false,
                "showSearch": false,
                "searchQuery": ""
              },
              "icon": "lucide-list",
              "title": "基于张祥前统一场论的引力常数G与光速c关系推导及理论验证引力光速统一方程 的大纲"
            }
          },
          {
            "id": "cc212266e8002a60",
            "type": "leaf",
            "state": {
              "type": "advanced-tables-toolbar",
              "state": {},
              "icon": "spreadsheet",
              "title": "Advanced Tables"
            }
          }
        ],
        "currentTab": 4
      }
    ],
    "direction": "horizontal",
    "width": 239.5
  },
  "left-ribbon": {
    "hiddenItems": {
      "switcher:打开快速切换": false,
      "graph:查看关系图谱": false,
      "canvas:新建白板": false,
      "daily-notes:打开/创建今天的日记": false,
      "templates:插入模板": false,
      "command-palette:打开命令面板": false,
      "bases:创建新数据库": false,
      "markdown-table-editor:Open Markdown Table Editor": false,
      "table-editor-obsidian:Advanced Tables Toolbar": false,
      "templater-obsidian:Templater": false,
      "obsidian-excalidraw-plugin:新建绘图文件": false,
      "translate:Open translation view": false
    }
  },
  "active": "ae905018e9ddedf3",
  "lastOpenFiles": [
    "utf/引力光速统一方程/基于张祥前统一场论的引力常数G与光速c关系推导及理论验证引力光速统一方程.md",
    "utf/引力光速统一方程/引力光速统一方程从空间动力学原理到常数统一的理论推导与验证.md",
    "utf/引力光速统一方程/统一场论框架下万有引力常数与光速的涌现性及其量子力学本质.md",
    "utf/引力光速统一方程/Gravitational Light Speed Unification Equation Theoretical Derivation and Verification from Spatial Dynamics Principles to Constant Unification.md",
    "utf/引力光速统一方程/replace_9_4_4_5.ps1",
    "utf/统一场论核心公式/01-时空同一化方程/_tmp_39052_16ee3e039deb98feb22cbd0550ccb196",
    "utf/引力光速统一方程/temp_9_4_4_5_english.md",
    "utf/引力光速统一方程/temp_9_4_4_5_chinese.md",
    "math/微积分/误差.py",
    "math/微积分",
    "math",
    "utf/引力光速统一方程/temp_isotropic_integration_en.md",
    "utf/引力光速统一方程/temp_isotropic_integration.md",
    "utf/引力光速统一方程/temp_chapter4.md",
    "utf/引力光速统一方程/temp_chapter3.md",
    "utf/引力光速统一方程/Emergence of the Gravitational Constant and the Speed of Light within the Framework of Unified Field Theory and Their Quantum Mechanical Essence.md",
    "utf/引力光速统一方程/temp_chapter2.md",
    "utf/引力光速统一方程/temp_chapter1.md",
    "utf/引力光速统一方程/temp_chapter17.md",
    "utf/引力光速统一方程/temp_chapter16.md",
    "utf/引力光速统一方程/temp_chapter15.md",
    "utf/引力光速统一方程/temp_chapter14.md",
    "utf/引力光速统一方程/Gravity-Light Speed Unification Equation - Theoretical Derivation and Verification from Spatial Dynamics Principles to Constant Unification.md",
    "utf/引力光速统一方程/Gravity-Light Speed Unification Equation Theoretical Derivation and Verification from Spatial Dynamics Principles to Constant Unification.md",
    "utf/引力光速统一方程/引力光速统一方程 - 从空间动力学原理到常数统一的理论推导与验证.md",
    "utf/引力光速统一方程/README.md",
    "utf/引力光速统一方程/引力光速统一方程：从空间动力学原理到常数统一的理论推导与验证.md",
    "utf/引力光速统一方程/Gravity-Light Speed Unification Equation",
    "utf/统一场论核心公式/01-时空同一化方程/_tmp_30952_7dd91cc79324ee88e8f83f22f6c24906",
    "utf/引力光速统一方程/引力光速的关系/论文分析与修复报告.md",
    "utf/引力光速统一方程/引力光速的关系/分析与修复/论文分析与修复报告.md",
    "utf/引力光速统一方程/引力光速的关系/分析与修复/引力光速统一方程论文_综合优化版.md",
    "utf/引力光速统一方程/引力光速的关系/分析与修复",
    "utf/引力光速统一方程/引力光速的关系/论文分析与优化建议",
    "utf/引力光速统一方程/引力光速的关系/引力光速统一方程论文.tex",
    "几何因子问题全面分析.png",
    "geometric_correction_factor_2_animation.svg",
    "complete_error_analysis.png",
    "geometric_factor_verification.png",
    "geometric_factor_summary.png",
    "几何因子推导总结.png",
    "几何因子数学总结.png",
    "张祥前统一场论_几何因子推导.png",
    "solid_angle_geometry.png",
    "立体角几何关系.png",
    "未命名.canvas",
    "未命名 1.canvas"
  ]
}